fbchatbot/__init__.py
fbchatbot/base_plugin/__init__.py
fbchatbot/base_plugin/listeners.py
fbchatbot/base_plugin/plugin.py
fbchatbot/command.py
fbchatbot/core_commands.py
fbchatbot/core_events.py
fbchatbot/events_handler.py
fbchatbot/fbchatbot.py
fbchatbot/plugin.py
fbchatbot/types_util.py
fbchatbot/util.py
fbchatbot-0.1.0.dist-info/WHEEL
fbchatbot-0.1.0.dist-info/METADATA
fbchatbot-0.1.0.dist-info/RECORD
